scLTkit/__init__.py
scLTkit/scLTAnalyses.py
scLTkit/scLTStatistics.py
scLTkit/utils.py
scLTkit-0.0.2.dist-info/METADATA
scLTkit-0.0.2.dist-info/WHEEL
scLTkit-0.0.2.dist-info/top_level.txt
scLTkit-0.0.2.dist-info/RECORD
